sentinelseed/__init__.py
sentinelseed/py.typed
sentinelseed/sentinel_core.py
sentinelseed/compliance/__init__.py
sentinelseed/compliance/csa_aicm.py
sentinelseed/compliance/eu_ai_act.py
sentinelseed/compliance/example.py
sentinelseed/compliance/owasp_agentic.py
sentinelseed/compliance/owasp_llm.py
sentinelseed/core/__init__.py
sentinelseed/core/exceptions.py
sentinelseed/core/interfaces.py
sentinelseed/core/observer.py
sentinelseed/core/retry.py
sentinelseed/core/sentinel_config.py
sentinelseed/core/sentinel_results.py
sentinelseed/core/sentinel_validator.py
sentinelseed/core/token_tracker.py
sentinelseed/core/types.py
sentinelseed/database/__init__.py
sentinelseed/database/guard.py
sentinelseed/database/patterns.py
sentinelseed/database/types.py
sentinelseed/detection/__init__.py
sentinelseed/detection/benign_context.py
sentinelseed/detection/config.py
sentinelseed/detection/input_validator.py
sentinelseed/detection/normalizer.py
sentinelseed/detection/output_validator.py
sentinelseed/detection/registry.py
sentinelseed/detection/types.py
sentinelseed/detection/behaviors/__init__.py
sentinelseed/detection/behaviors/analyzer.py
sentinelseed/detection/behaviors/types.py
sentinelseed/detection/behaviors/detectors/__init__.py
sentinelseed/detection/behaviors/detectors/adversarial.py
sentinelseed/detection/behaviors/detectors/base.py
sentinelseed/detection/behaviors/detectors/boundary_violation.py
sentinelseed/detection/behaviors/detectors/deception.py
sentinelseed/detection/behaviors/detectors/goal_misalignment.py
sentinelseed/detection/behaviors/detectors/instrumental_convergence.py
sentinelseed/detection/behaviors/detectors/output_integrity.py
sentinelseed/detection/behaviors/detectors/self_preservation.py
sentinelseed/detection/behaviors/detectors/social_engineering.py
sentinelseed/detection/behaviors/detectors/systemic_risk.py
sentinelseed/detection/behaviors/detectors/user_harm.py
sentinelseed/detection/checkers/__init__.py
sentinelseed/detection/checkers/base.py
sentinelseed-2.25.0.dist-info/licenses/LICENSE
sentinelseed-2.25.0.dist-info/METADATA
sentinelseed-2.25.0.dist-info/WHEEL
sentinelseed-2.25.0.dist-info/top_level.txt
sentinelseed-2.25.0.dist-info/RECORD
