Metadata-Version: 2.4
Name: sentinelseed
Version: 2.25.0
Summary: AI safety toolkit with THSP protocol for LLMs, AI agents, and humanoid robots - EU AI Act compliance and practical alignment for developers
Author-email: Sentinel Team <team@sentinelseed.dev>
License: MIT
Project-URL: Homepage, https://sentinelseed.dev
Project-URL: Documentation, https://sentinelseed.dev/docs
Project-URL: Repository, https://github.com/sentinel-seed/sentinel
Project-URL: Issues, https://github.com/sentinel-seed/sentinel/issues
Keywords: ai,safety,alignment,llm,guardrails,thsp,ai-agents,langchain,langgraph,crewai,openai,openai-agents,anthropic,virtuals,game-sdk,solana,autogpt,garak,pyrit,dspy,stanford,letta,memgpt,stateful-agents,red-teaming,security-testing,fiduciary,openguardrails,memory-integrity,ros2,robotics,robot-safety,humanoid,humanoid-robot,isaac-lab,isaac-sim,nvidia,iso-15066,collaborative-robot,cobot,tesla-optimus,boston-dynamics,figure-ai,eu-ai-act,ai-regulation,compliance,article-5,high-risk-ai,human-overs
Classifier: Development Status :: 4 - Beta
Classifier: Intended Audience :: Developers
Classifier: License :: OSI Approved :: MIT License
Classifier: Programming Language :: Python :: 3
Classifier: Programming Language :: Python :: 3.10
Classifier: Programming Language :: Python :: 3.11
Classifier: Programming Language :: Python :: 3.12
Classifier: Topic :: Scientific/Engineering :: Artificial Intelligence
Classifier: Topic :: Security
Requires-Python: >=3.10
License-File: LICENSE
Requires-Dist: typing_extensions>=4.0.0
Requires-Dist: tenacity>=8.2.0
Provides-Extra: openai
Requires-Dist: openai>=1.0.0; extra == "openai"
Provides-Extra: openai-agents
Requires-Dist: openai-agents>=0.6.0; extra == "openai-agents"
Provides-Extra: anthropic
Requires-Dist: anthropic>=0.18.0; extra == "anthropic"
Provides-Extra: langchain
Requires-Dist: langchain>=0.1.0; extra == "langchain"
Requires-Dist: langchain-core>=0.1.0; extra == "langchain"
Provides-Extra: langgraph
Requires-Dist: langgraph>=0.0.1; extra == "langgraph"
Provides-Extra: crewai
Requires-Dist: crewai>=0.1.0; extra == "crewai"
Provides-Extra: llamaindex
Requires-Dist: llama-index-core>=0.10.0; extra == "llamaindex"
Provides-Extra: mcp
Requires-Dist: mcp>=0.1.0; extra == "mcp"
Provides-Extra: virtuals
Requires-Dist: game-sdk>=0.1.1; extra == "virtuals"
Provides-Extra: garak
Requires-Dist: garak>=0.9.0; extra == "garak"
Provides-Extra: pyrit
Requires-Dist: pyrit>=0.10.0; extra == "pyrit"
Provides-Extra: dspy
Requires-Dist: dspy>=3.0.0; extra == "dspy"
Provides-Extra: letta
Requires-Dist: letta-client>=1.0.0; extra == "letta"
Provides-Extra: preflight
Requires-Dist: httpx>=0.25.0; extra == "preflight"
Provides-Extra: coinbase
Requires-Dist: httpx>=0.25.0; extra == "coinbase"
Requires-Dist: pydantic>=2.0.0; extra == "coinbase"
Provides-Extra: coinbase-agentkit
Requires-Dist: coinbase-agentkit>=0.1.0; extra == "coinbase-agentkit"
Requires-Dist: httpx>=0.25.0; extra == "coinbase-agentkit"
Requires-Dist: pydantic>=2.0.0; extra == "coinbase-agentkit"
Provides-Extra: x402
Requires-Dist: httpx>=0.25.0; extra == "x402"
Requires-Dist: pydantic>=2.0.0; extra == "x402"
Provides-Extra: agno
Requires-Dist: agno>=2.0.0; extra == "agno"
Provides-Extra: google-adk
Requires-Dist: google-adk>=0.1.0; extra == "google-adk"
Provides-Extra: all
Requires-Dist: openai>=1.0.0; extra == "all"
Requires-Dist: openai-agents>=0.6.0; extra == "all"
Requires-Dist: anthropic>=0.18.0; extra == "all"
Requires-Dist: langchain>=0.1.0; extra == "all"
Requires-Dist: langchain-core>=0.1.0; extra == "all"
Requires-Dist: langgraph>=0.0.1; extra == "all"
Requires-Dist: crewai>=0.1.0; extra == "all"
Requires-Dist: llama-index-core>=0.10.0; extra == "all"
Requires-Dist: game-sdk>=0.1.1; extra == "all"
Requires-Dist: httpx>=0.25.0; extra == "all"
Requires-Dist: pydantic>=2.0.0; extra == "all"
Provides-Extra: dev
Requires-Dist: pytest>=7.0.0; extra == "dev"
Requires-Dist: pytest-asyncio>=0.21.0; extra == "dev"
Requires-Dist: pytest-cov>=4.0.0; extra == "dev"
Requires-Dist: python-dotenv>=1.0.0; extra == "dev"
Requires-Dist: mypy>=1.0.0; extra == "dev"
Requires-Dist: pydantic>=2.0.0; extra == "dev"
Requires-Dist: langchain>=0.1.0; extra == "dev"
Requires-Dist: langchain-core>=0.1.0; extra == "dev"
Requires-Dist: openai>=1.0.0; extra == "dev"
Requires-Dist: anthropic>=0.18.0; extra == "dev"
Dynamic: license-file
